langgraph_wave_orchestrator/__init__.py
langgraph_wave_orchestrator/models.py
langgraph_wave_orchestrator/prompts.py
langgraph_wave_orchestrator/state_manager.py
langgraph_wave_orchestrator/wave_manager.py
langgraph_wave_orchestrator/wave_orchestrator.py
langgraph_wave_orchestrator/worker_manager.py
lanngraph_wave_orchestrator-1.1.8.dist-info/METADATA
lanngraph_wave_orchestrator-1.1.8.dist-info/WHEEL
lanngraph_wave_orchestrator-1.1.8.dist-info/RECORD
