Metadata-Version: 2.4
Name: Lanngraph-Wave-Orchestrator
Version: 1.1.8
Summary: Add your description here
Requires-Python: >=3.11
Requires-Dist: langchain-core>=0.1.0
Requires-Dist: langchain-openai>=0.0.1
Requires-Dist: langgraph-cli[inmem]>=0.1.0
Requires-Dist: langgraph>=0.1.0
Requires-Dist: pydantic>=2.0.0
Requires-Dist: python-dotenv>=1.0.0
